tr3/__init__.py
tr3/tr3.py
tr3-1.6.dist-info/LICENSE
tr3-1.6.dist-info/METADATA
tr3-1.6.dist-info/WHEEL
tr3-1.6.dist-info/RECORD
