Metadata-Version: 2.1
Name: tr3
Version: 1.6
Summary: tr3
Home-page: https://github.com/nfredrik/tr3
Author: fredrik
Author-email: nfredrik@hotmail.com
Requires-Python: >=3.12,<4.0
Classifier: Programming Language :: Python :: 3
Classifier: Programming Language :: Python :: 3.12
Project-URL: Bug Tracker, https://github.com/your-username/your-repo/issues
Project-URL: Documentation, https://icanhazdadjoke.com/
Project-URL: Repository, https://github.com/nfredrik/tr3
Project-URL: Source Code, https://github.com/nfredrik/tr3
